mypermobil/__init__.py
mypermobil/const.py
mypermobil/mypermobil.py
mypermobil/py.typed
mypermobil-0.1.8.dist-info/LICENSE
mypermobil-0.1.8.dist-info/METADATA
mypermobil-0.1.8.dist-info/WHEEL
mypermobil-0.1.8.dist-info/top_level.txt
mypermobil-0.1.8.dist-info/RECORD
