Metadata-Version: 2.1
Name: mypermobil
Version: 0.1.8
Summary: A Python wrapper for the MyPermobil API
Home-page: https://github.com/IsakNyberg/MyPermobil-API
Author: Isak Nyberg
Author-email: isak@nyberg.dev
License: MIT
Project-URL: Bug Tracker, https://github.com/IsakNyberg/MyPermobil-API/issues
Project-URL: repository, https://github.com/IsakNyberg/MyPermobil-API
Requires-Python: >=3.6
License-File: LICENSE
Requires-Dist: aiohttp
Requires-Dist: aiocache
